sphinx_glpi_theme/__init__.py
sphinx_glpi_theme/glpi/layout.html
sphinx_glpi_theme/glpi/theme.conf
sphinx_glpi_theme/glpi/static/glpi.css
sphinx_glpi_theme/glpi/static/jquery.fancybox.min.css
sphinx_glpi_theme/glpi/static/jquery.fancybox.min.js
sphinx_glpi_theme/glpi/static/jquery.js
sphinx_glpi_theme/glpi/static/images/glpi.png
sphinx_glpi_theme/local_rtd_theme/__init__.py
sphinx_glpi_theme/local_rtd_theme/breadcrumbs.html
sphinx_glpi_theme/local_rtd_theme/footer.html
sphinx_glpi_theme/local_rtd_theme/layout.html
sphinx_glpi_theme/local_rtd_theme/layout_BACKUP_136878.html
sphinx_glpi_theme/local_rtd_theme/layout_BASE_136878.html
sphinx_glpi_theme/local_rtd_theme/layout_LOCAL_136878.html
sphinx_glpi_theme/local_rtd_theme/layout_REMOTE_136878.html
sphinx_glpi_theme/local_rtd_theme/search.html
sphinx_glpi_theme/local_rtd_theme/searchbox.html
sphinx_glpi_theme/local_rtd_theme/theme.conf
sphinx_glpi_theme/local_rtd_theme/versions.html
sphinx_glpi_theme/local_rtd_theme/static/css/badge_only.css
sphinx_glpi_theme/local_rtd_theme/static/css/theme.css
sphinx_glpi_theme/local_rtd_theme/static/css/fonts/Roboto-Slab-Bold.woff
sphinx_glpi_theme/local_rtd_theme/static/css/fonts/Roboto-Slab-Bold.woff2
sphinx_glpi_theme/local_rtd_theme/static/css/fonts/Roboto-Slab-Regular.woff
sphinx_glpi_theme/local_rtd_theme/static/css/fonts/Roboto-Slab-Regular.woff2
sphinx_glpi_theme/local_rtd_theme/static/css/fonts/fontawesome-webfont.eot
sphinx_glpi_theme/local_rtd_theme/static/css/fonts/fontawesome-webfont.svg
sphinx_glpi_theme/local_rtd_theme/static/css/fonts/fontawesome-webfont.ttf
sphinx_glpi_theme/local_rtd_theme/static/css/fonts/fontawesome-webfont.woff
sphinx_glpi_theme/local_rtd_theme/static/css/fonts/fontawesome-webfont.woff2
sphinx_glpi_theme/local_rtd_theme/static/css/fonts/lato-bold-italic.woff
sphinx_glpi_theme/local_rtd_theme/static/css/fonts/lato-bold-italic.woff2
sphinx_glpi_theme/local_rtd_theme/static/css/fonts/lato-bold.woff
sphinx_glpi_theme-0.6.dist-info/LICENSE
sphinx_glpi_theme-0.6.dist-info/METADATA
sphinx_glpi_theme-0.6.dist-info/WHEEL
sphinx_glpi_theme-0.6.dist-info/top_level.txt
sphinx_glpi_theme-0.6.dist-info/RECORD
